mediaaccount/__init__.py
mediaaccount/apiclient.py
mediaaccount/models.py
mediaaccount-0.8.14.dist-info/LICENSE
mediaaccount-0.8.14.dist-info/METADATA
mediaaccount-0.8.14.dist-info/WHEEL
mediaaccount-0.8.14.dist-info/top_level.txt
mediaaccount-0.8.14.dist-info/RECORD
