Metadata-Version: 2.1
Name: mediaaccount
Version: 0.8.14
Summary: Provides easy Acces to MediaAccount Api
Home-page: https://github.com/ckrowiorsch/mediaaccount-py
Author: Christian Krowiorsch
Project-URL: Bug Tracker, https://github.com/ckrowiorsch/mediaaccount-py/issues
Classifier: Programming Language :: Python :: 3
Classifier: Programming Language :: Python :: 3.6
Classifier: License :: OSI Approved :: MIT License
Classifier: Operating System :: OS Independent
Requires-Python: >=3.6
License-File: LICENSE
